<?xml version="1.0" encoding="utf-8" standalone="yes"?>
<Gesture Name = "rectangle">
	<Stroke>
		<Point X = "303.1323" Y = "-897.5237" T = "0" Pressure = "0" />
		<Point X = "303.1323" Y = "-897.5237" T = "0" Pressure = "0" />
		<Point X = "305.6347" Y = "-875.0025" T = "0" Pressure = "0" />
		<Point X = "305.6347" Y = "-834.9649" T = "0" Pressure = "0" />
		<Point X = "305.6347" Y = "-814.946" T = "0" Pressure = "0" />
		<Point X = "305.6347" Y = "-763.6478" T = "0" Pressure = "0" />
		<Point X = "305.6347" Y = "-738.6243" T = "0" Pressure = "0" />
		<Point X = "305.6347" Y = "-709.8472" T = "0" Pressure = "0" />
		<Point X = "305.6347" Y = "-648.5396" T = "0" Pressure = "0" />
		<Point X = "305.6347" Y = "-627.2695" T = "0" Pressure = "0" />
		<Point X = "305.6347" Y = "-604.7484" T = "0" Pressure = "0" />
		<Point X = "305.6347" Y = "-604.7484" T = "0" Pressure = "0" />
		<Point X = "304.3835" Y = "-570.9666" T = "0" Pressure = "0" />
		<Point X = "304.3835" Y = "-562.2084" T = "0" Pressure = "0" />
		<Point X = "303.1323" Y = "-553.4501" T = "0" Pressure = "0" />
		<Point X = "303.1323" Y = "-540.9384" T = "0" Pressure = "0" />
		<Point X = "303.1323" Y = "-537.1848" T = "0" Pressure = "0" />
		<Point X = "303.1323" Y = "-533.4313" T = "0" Pressure = "0" />
		<Point X = "303.1323" Y = "-532.1801" T = "0" Pressure = "0" />
		<Point X = "303.1323" Y = "-530.929" T = "0" Pressure = "0" />
		<Point X = "303.1323" Y = "-529.6778" T = "0" Pressure = "0" />
		<Point X = "303.1323" Y = "-529.6778" T = "0" Pressure = "0" />
		<Point X = "303.1323" Y = "-529.6778" T = "0" Pressure = "0" />
		<Point X = "303.1323" Y = "-529.6778" T = "0" Pressure = "0" />
		<Point X = "303.1323" Y = "-529.6778" T = "0" Pressure = "0" />
		<Point X = "303.1323" Y = "-529.6778" T = "0" Pressure = "0" />
		<Point X = "301.8812" Y = "-529.6778" T = "0" Pressure = "0" />
		<Point X = "301.8812" Y = "-527.1754" T = "0" Pressure = "0" />
		<Point X = "339.4164" Y = "-528.4266" T = "0" Pressure = "0" />
		<Point X = "371.9471" Y = "-534.6824" T = "0" Pressure = "0" />
		<Point X = "410.7335" Y = "-540.9384" T = "0" Pressure = "0" />
		<Point X = "492.06" Y = "-550.9478" T = "0" Pressure = "0" />
		<Point X = "559.6235" Y = "-554.7013" T = "0" Pressure = "0" />
		<Point X = "575.8889" Y = "-554.7013" T = "0" Pressure = "0" />
		<Point X = "589.6518" Y = "-554.7013" T = "0" Pressure = "0" />
		<Point X = "594.6565" Y = "-554.7013" T = "0" Pressure = "0" />
		<Point X = "599.6611" Y = "-554.7013" T = "0" Pressure = "0" />
		<Point X = "599.6611" Y = "-553.4501" T = "0" Pressure = "0" />
		<Point X = "599.6611" Y = "-553.4501" T = "0" Pressure = "0" />
		<Point X = "599.6611" Y = "-553.4501" T = "0" Pressure = "0" />
		<Point X = "599.6611" Y = "-553.4501" T = "0" Pressure = "0" />
		<Point X = "599.6611" Y = "-553.4501" T = "0" Pressure = "0" />
		<Point X = "599.6611" Y = "-553.4501" T = "0" Pressure = "0" />
		<Point X = "599.6611" Y = "-553.4501" T = "0" Pressure = "0" />
		<Point X = "599.6611" Y = "-553.4501" T = "0" Pressure = "0" />
		<Point X = "599.6611" Y = "-553.4501" T = "0" Pressure = "0" />
		<Point X = "599.6611" Y = "-553.4501" T = "0" Pressure = "0" />
		<Point X = "599.6611" Y = "-553.4501" T = "0" Pressure = "0" />
		<Point X = "599.6611" Y = "-559.7061" T = "0" Pressure = "0" />
		<Point X = "599.6611" Y = "-559.7061" T = "0" Pressure = "0" />
		<Point X = "599.6611" Y = "-562.2084" T = "0" Pressure = "0" />
		<Point X = "598.41" Y = "-570.9666" T = "0" Pressure = "0" />
		<Point X = "598.41" Y = "-577.2225" T = "0" Pressure = "0" />
		<Point X = "597.1588" Y = "-607.2507" T = "0" Pressure = "0" />
		<Point X = "597.1588" Y = "-619.7625" T = "0" Pressure = "0" />
		<Point X = "595.9077" Y = "-653.5443" T = "0" Pressure = "0" />
		<Point X = "595.9077" Y = "-671.0607" T = "0" Pressure = "0" />
		<Point X = "595.9077" Y = "-689.8284" T = "0" Pressure = "0" />
		<Point X = "595.9077" Y = "-733.6196" T = "0" Pressure = "0" />
		<Point X = "595.9077" Y = "-783.6666" T = "0" Pressure = "0" />
		<Point X = "595.9077" Y = "-804.9367" T = "0" Pressure = "0" />
		<Point X = "595.9077" Y = "-827.4578" T = "0" Pressure = "0" />
		<Point X = "595.9077" Y = "-872.5002" T = "0" Pressure = "0" />
		<Point X = "595.9077" Y = "-872.5002" T = "0" Pressure = "0" />
		<Point X = "595.9077" Y = "-906.2819" T = "0" Pressure = "0" />
		<Point X = "595.9077" Y = "-933.8079" T = "0" Pressure = "0" />
		<Point X = "592.1541" Y = "-948.822" T = "0" Pressure = "0" />
		<Point X = "592.1541" Y = "-955.0778" T = "0" Pressure = "0" />
		<Point X = "590.903" Y = "-962.5849" T = "0" Pressure = "0" />
		<Point X = "590.903" Y = "-966.3384" T = "0" Pressure = "0" />
		<Point X = "590.903" Y = "-966.3384" T = "0" Pressure = "0" />
		<Point X = "590.903" Y = "-967.5896" T = "0" Pressure = "0" />
		<Point X = "590.903" Y = "-967.5896" T = "0" Pressure = "0" />
		<Point X = "590.903" Y = "-967.5896" T = "0" Pressure = "0" />
		<Point X = "590.903" Y = "-967.5896" T = "0" Pressure = "0" />
		<Point X = "590.903" Y = "-967.5896" T = "0" Pressure = "0" />
		<Point X = "590.903" Y = "-967.5896" T = "0" Pressure = "0" />
		<Point X = "590.903" Y = "-967.5896" T = "0" Pressure = "0" />
		<Point X = "590.903" Y = "-967.5896" T = "0" Pressure = "0" />
		<Point X = "590.903" Y = "-967.5896" T = "0" Pressure = "0" />
		<Point X = "590.903" Y = "-967.5896" T = "0" Pressure = "0" />
		<Point X = "590.903" Y = "-967.5896" T = "0" Pressure = "0" />
		<Point X = "590.903" Y = "-967.5896" T = "0" Pressure = "0" />
		<Point X = "590.903" Y = "-967.5896" T = "0" Pressure = "0" />
		<Point X = "590.903" Y = "-967.5896" T = "0" Pressure = "0" />
		<Point X = "590.903" Y = "-967.5896" T = "0" Pressure = "0" />
		<Point X = "590.903" Y = "-967.5896" T = "0" Pressure = "0" />
		<Point X = "588.4006" Y = "-967.5896" T = "0" Pressure = "0" />
		<Point X = "582.1447" Y = "-967.5896" T = "0" Pressure = "0" />
		<Point X = "564.6282" Y = "-967.5896" T = "0" Pressure = "0" />
		<Point X = "552.1165" Y = "-967.5896" T = "0" Pressure = "0" />
		<Point X = "532.0977" Y = "-967.5896" T = "0" Pressure = "0" />
		<Point X = "508.3253" Y = "-967.5896" T = "0" Pressure = "0" />
		<Point X = "490.8088" Y = "-967.5896" T = "0" Pressure = "0" />
		<Point X = "468.2877" Y = "-967.5896" T = "0" Pressure = "0" />
		<Point X = "433.2546" Y = "-967.5896" T = "0" Pressure = "0" />
		<Point X = "413.2358" Y = "-965.0873" T = "0" Pressure = "0" />
		<Point X = "396.9706" Y = "-965.0873" T = "0" Pressure = "0" />
		<Point X = "360.6864" Y = "-962.5849" T = "0" Pressure = "0" />
		<Point X = "360.6864" Y = "-962.5849" T = "0" Pressure = "0" />
		<Point X = "340.6676" Y = "-961.3337" T = "0" Pressure = "0" />
		<Point X = "340.6676" Y = "-961.3337" T = "0" Pressure = "0" />
		<Point X = "319.3976" Y = "-956.329" T = "0" Pressure = "0" />
		<Point X = "314.3929" Y = "-955.0778" T = "0" Pressure = "0" />
		<Point X = "310.6394" Y = "-955.0778" T = "0" Pressure = "0" />
		<Point X = "310.6394" Y = "-955.0778" T = "0" Pressure = "0" />
		<Point X = "309.3882" Y = "-955.0778" T = "0" Pressure = "0" />
		<Point X = "309.3882" Y = "-955.0778" T = "0" Pressure = "0" />
		<Point X = "309.3882" Y = "-955.0778" T = "0" Pressure = "0" />
		<Point X = "309.3882" Y = "-955.0778" T = "0" Pressure = "0" />
		<Point X = "309.3882" Y = "-955.0778" T = "0" Pressure = "0" />
		<Point X = "309.3882" Y = "-955.0778" T = "0" Pressure = "0" />
		<Point X = "308.137" Y = "-955.0778" T = "0" Pressure = "0" />
		<Point X = "305.6347" Y = "-955.0778" T = "0" Pressure = "0" />
		<Point X = "304.3835" Y = "-955.0778" T = "0" Pressure = "0" />
		<Point X = "304.3835" Y = "-955.0778" T = "0" Pressure = "0" />
		<Point X = "303.1323" Y = "-955.0778" T = "0" Pressure = "0" />
		<Point X = "303.1323" Y = "-955.0778" T = "0" Pressure = "0" />
		<Point X = "301.8812" Y = "-955.0778" T = "0" Pressure = "0" />
		<Point X = "301.8812" Y = "-955.0778" T = "0" Pressure = "0" />
		<Point X = "301.8812" Y = "-955.0778" T = "0" Pressure = "0" />
		<Point X = "301.8812" Y = "-955.0778" T = "0" Pressure = "0" />
		<Point X = "301.8812" Y = "-955.0778" T = "0" Pressure = "0" />
		<Point X = "301.8812" Y = "-955.0778" T = "0" Pressure = "0" />
		<Point X = "301.8812" Y = "-955.0778" T = "0" Pressure = "0" />
		<Point X = "301.8812" Y = "-955.0778" T = "0" Pressure = "0" />
		<Point X = "301.8812" Y = "-955.0778" T = "0" Pressure = "0" />
		<Point X = "301.8812" Y = "-955.0778" T = "0" Pressure = "0" />
		<Point X = "301.8812" Y = "-955.0778" T = "0" Pressure = "0" />
		<Point X = "301.8812" Y = "-955.0778" T = "0" Pressure = "0" />
		<Point X = "301.8812" Y = "-955.0778" T = "0" Pressure = "0" />
		<Point X = "301.8812" Y = "-955.0778" T = "0" Pressure = "0" />
		<Point X = "301.8812" Y = "-955.0778" T = "0" Pressure = "0" />
		<Point X = "301.8812" Y = "-955.0778" T = "0" Pressure = "0" />
		<Point X = "301.8812" Y = "-953.8267" T = "0" Pressure = "0" />
		<Point X = "300.63" Y = "-940.0637" T = "0" Pressure = "0" />
		<Point X = "299.3788" Y = "-932.5567" T = "0" Pressure = "0" />
		<Point X = "298.1276" Y = "-925.0496" T = "0" Pressure = "0" />
		<Point X = "293.1229" Y = "-906.2819" T = "0" Pressure = "0" />
		<Point X = "293.1229" Y = "-906.2819" T = "0" Pressure = "0" />
		<Point X = "291.8717" Y = "-897.5237" T = "0" Pressure = "0" />
		<Point X = "291.8717" Y = "-888.7655" T = "0" Pressure = "0" />
		<Point X = "291.8717" Y = "-883.7608" T = "0" Pressure = "0" />
		<Point X = "291.8717" Y = "-881.2585" T = "0" Pressure = "0" />
		<Point X = "291.8717" Y = "-880.0073" T = "0" Pressure = "0" />
		<Point X = "291.8717" Y = "-880.0073" T = "0" Pressure = "0" />
		<Point X = "291.8717" Y = "-880.0073" T = "0" Pressure = "0" />
		<Point X = "291.8717" Y = "-880.0073" T = "0" Pressure = "0" />
		<Point X = "291.8717" Y = "-880.0073" T = "0" Pressure = "0" />
		<Point X = "291.8717" Y = "-880.0073" T = "0" Pressure = "0" />
		<Point X = "291.8717" Y = "-880.0073" T = "0" Pressure = "0" />
		<Point X = "291.8717" Y = "-880.0073" T = "0" Pressure = "0" />
		<Point X = "291.8717" Y = "-880.0073" T = "0" Pressure = "0" />
		<Point X = "291.8717" Y = "-880.0073" T = "0" Pressure = "0" />
		<Point X = "291.8717" Y = "-880.0073" T = "0" Pressure = "0" />
		<Point X = "291.8717" Y = "-880.0073" T = "0" Pressure = "0" />
		<Point X = "291.8717" Y = "-880.0073" T = "0" Pressure = "0" />
		<Point X = "291.8717" Y = "-880.0073" T = "0" Pressure = "0" />
		<Point X = "291.8717" Y = "-880.0073" T = "0" Pressure = "0" />
		<Point X = "291.8717" Y = "-880.0073" T = "0" Pressure = "0" />
	</Stroke>
</Gesture>
